stackit/dns/__init__.py
stackit/dns/api/__init__.py
stackit/dns/api/default_api.py
stackit/dns/api_client.py
stackit/dns/api_response.py
stackit/dns/configuration.py
stackit/dns/exceptions.py
stackit/dns/models/__init__.py
stackit/dns/models/clone_zone_payload.py
stackit/dns/models/create_label_payload.py
stackit/dns/models/create_label_response.py
stackit/dns/models/create_record_set_payload.py
stackit/dns/models/create_zone_payload.py
stackit/dns/models/delete_label_response.py
stackit/dns/models/domain_extensions.py
stackit/dns/models/domain_observability_extension.py
stackit/dns/models/error_message.py
stackit/dns/models/export_record_sets_payload.py
stackit/dns/models/import_record_sets_payload.py
stackit/dns/models/import_record_sets_response.py
stackit/dns/models/import_summary.py
stackit/dns/models/label.py
stackit/dns/models/list_labels_response.py
stackit/dns/models/list_record_sets_response.py
stackit/dns/models/list_zones_response.py
stackit/dns/models/message.py
stackit/dns/models/move_code_response.py
stackit/dns/models/move_zone_payload.py
stackit/dns/models/partial_update_record_payload.py
stackit/dns/models/partial_update_record_set_payload.py
stackit/dns/models/partial_update_zone_payload.py
stackit/dns/models/record.py
stackit/dns/models/record_data_exchange.py
stackit/dns/models/record_payload.py
stackit/dns/models/record_set.py
stackit/dns/models/record_set_response.py
stackit/dns/models/validate_move_code_payload.py
stackit/dns/models/zone.py
stackit/dns/models/zone_data_exchange.py
stackit/dns/models/zone_extensions.py
stackit/dns/models/zone_models_import_record_model.py
stackit/dns/models/zone_models_import_zone_json.py
stackit/dns/models/zone_observability_extension.py
stackit/dns/models/zone_response.py
stackit/dns/py.typed
stackit/dns/rest.py
stackit_dns-0.5.0.dist-info/LICENSE.md
stackit_dns-0.5.0.dist-info/METADATA
stackit_dns-0.5.0.dist-info/NOTICE.txt
stackit_dns-0.5.0.dist-info/WHEEL
stackit_dns-0.5.0.dist-info/RECORD
